setup.cfg
setup.py
AWS_Manager.egg-info/PKG-INFO
AWS_Manager.egg-info/SOURCES.txt
AWS_Manager.egg-info/dependency_links.txt
AWS_Manager.egg-info/entry_points.txt
AWS_Manager.egg-info/not-zip-safe
AWS_Manager.egg-info/requires.txt
AWS_Manager.egg-info/top_level.txt
aws_manager/__init__.py
aws_manager/main.py
aws_manager/aws/__init__.py
aws_manager/aws/aws.py
aws_manager/aws/aws_credentials.py
aws_manager/config_file/__init__.py
aws_manager/config_file/config.py
aws_manager/functions/__init__.py
aws_manager/functions/functions.py
aws_manager/menus/__init__.py
aws_manager/menus/menus.py
aws_manager/settings/__init__.py
aws_manager/settings/settings.py