Metadata-Version: 1.0
Name: AWS-Manager
Version: 0.3b0
Summary: An open source project for managing your AWS resources easily in your day to day coding
Home-page: UNKNOWN
Author: ('Asaf Nevo, Aviv Paz',)
Author-email: asafnevo1@gmail.com, avivpaz43556@gmail.com
License: GNU
Keywords: aws ec2 amazon servers vpc awscli
Platform: UNKNOWN
